qec_util/__init__.py
qec_util/circuits/__init__.py
qec_util/circuits/circuits.py
qec_util/data_processing/__init__.py
qec_util/data_processing/pij_matrix.py
qec_util/data_processing/syndrome.py
qec_util/dem_instrs/__init__.py
qec_util/dem_instrs/dem_instrs.py
qec_util/dem_instrs/hyperedge_decomposition.py
qec_util/dem_instrs/util.py
qec_util/dems/__init__.py
qec_util/dems/dems.py
qec_util/dems/hyperedge_decomposition.py
qec_util/distance/__init__.py
qec_util/distance/distance.py
qec_util/mod2/__init__.py
qec_util/mod2/util.py
qec_util/performance/__init__.py
qec_util/performance/metrics.py
qec_util/performance/plots.py
qec_util/samplers/__init__.py
qec_util/samplers/samplers.py
qec_util/threshold/__init__.py
qec_util/threshold/estimation.py
qec_util/threshold/plot.py
qec_util/threshold/util.py
qec_util-0.4.2.dist-info/licenses/LICENSE
qec_util-0.4.2.dist-info/METADATA
qec_util-0.4.2.dist-info/WHEEL
qec_util-0.4.2.dist-info/top_level.txt
qec_util-0.4.2.dist-info/RECORD
