Metadata-Version: 2.4
Name: qec-util
Version: 0.4.2
Summary: Useful tools for QEC simulation
Author-email: Marc Serra Peralta <marcserraperalta@gmail.com>, Boris Varbanov <b.m.varbanov@gmail.com>
Maintainer-email: Marc Serra Peralta <marcserraperalta@gmail.com>
License: MIT License
Requires-Python: >=3.10
License-File: LICENSE
Requires-Dist: numpy
Requires-Dist: stim
Requires-Dist: lmfit
Requires-Dist: xarray
Provides-Extra: dev
Requires-Dist: qec_util[all]; extra == "dev"
Requires-Dist: pip-tools; extra == "dev"
Requires-Dist: pytest; extra == "dev"
Requires-Dist: scalene; extra == "dev"
Requires-Dist: black; extra == "dev"
Requires-Dist: pytest-black; extra == "dev"
Provides-Extra: all
Requires-Dist: networkx; extra == "all"
Requires-Dist: gurobipy; extra == "all"
Requires-Dist: scipy; extra == "all"
Requires-Dist: pymatching; extra == "all"
Requires-Dist: dem_decoders; extra == "all"
Requires-Dist: pyyaml; extra == "all"
Requires-Dist: matplotlib; extra == "all"
Requires-Dist: galois; extra == "all"
Dynamic: license-file
